README.rst
setup.py
keyword_ranker/__init__.py
keyword_ranker/kwr.py
keyword_ranker/rake.py
keyword_ranker/smartstoplist.txt
keyword_ranker.egg-info/PKG-INFO
keyword_ranker.egg-info/SOURCES.txt
keyword_ranker.egg-info/dependency_links.txt
keyword_ranker.egg-info/not-zip-safe
keyword_ranker.egg-info/requires.txt
keyword_ranker.egg-info/top_level.txt