Metadata-Version: 1.0
Name: keyword-ranker
Version: 0.2
Summary: Python implementation ranking keywords from a corpus with with respect to other text files using the Rapid Automatic Keyword Exctraction algorithm.
Home-page: https://github.com/sbadecker/keyword_ranker
Author: Stefan Decker
Author-email: sba.decker@gmail.com
License: MIT
Keywords: nlp text-mining algorithms
Platform: UNKNOWN
